wp_toolbox/Elements.py
wp_toolbox/Searchengine.py
wp_toolbox/__init__.py
wp_toolbox-0.4.1.dist-info/WHEEL
wp_toolbox-0.4.1.dist-info/METADATA
wp_toolbox-0.4.1.dist-info/RECORD
