Metadata-Version: 2.1
Name: wp-toolbox
Version: 0.4.1
Summary: Library for accessing linguistic annotated texts (https://wp-toolbox.thomas-zastrow.de)
Author: Thomas Zastrow
Author-email: thomas.zastrow@mpcdf.mpg.de
Requires-Python: >=3.7,<4.0
Classifier: Programming Language :: Python :: 3
Classifier: Programming Language :: Python :: 3.7
Classifier: Programming Language :: Python :: 3.8
Classifier: Programming Language :: Python :: 3.9
Requires-Dist: elasticsearch (>=7.12.1,<8.0.0)
